dgread_utils.py
dgread.cpython-39-darwin.so
dgread-1.1.5.dist-info/RECORD
dgread-1.1.5.dist-info/WHEEL
dgread-1.1.5.dist-info/top_level.txt
dgread-1.1.5.dist-info/METADATA
