Metadata-Version: 2.4
Name: dgread
Version: 1.1.5
Summary: Python reader for dg/dgz dynamic group data files
Author-email: David Sheinberg <david_sheinberg@brown.edu>
License: MIT
Project-URL: Homepage, https://github.com/SheinbergLab/dgread
Project-URL: Documentation, https://github.com/SheinbergLab/dgread#readme
Project-URL: Repository, https://github.com/SheinbergLab/dgread
Project-URL: Issues, https://github.com/SheinbergLab/dgread/issues
Keywords: data,neuroscience,dynamic-groups,dg,dgz,science
Classifier: Development Status :: 5 - Production/Stable
Classifier: Intended Audience :: Science/Research
Classifier: License :: OSI Approved :: MIT License
Classifier: Operating System :: OS Independent
Classifier: Programming Language :: C
Classifier: Programming Language :: Python :: 3
Classifier: Programming Language :: Python :: 3.9
Classifier: Programming Language :: Python :: 3.10
Classifier: Programming Language :: Python :: 3.11
Classifier: Programming Language :: Python :: 3.12
Classifier: Programming Language :: Python :: 3.13
Classifier: Programming Language :: Python :: 3.14
Classifier: Topic :: Scientific/Engineering
Classifier: Topic :: Scientific/Engineering :: Bio-Informatics
Requires-Python: >=3.9
Requires-Dist: numpy>=1.19
Provides-Extra: pandas
Requires-Dist: pandas>=1.0; extra == "pandas"
Provides-Extra: dev
Requires-Dist: build; extra == "dev"
Requires-Dist: twine; extra == "dev"
Requires-Dist: pytest; extra == "dev"
Requires-Dist: cibuildwheel; extra == "dev"
Provides-Extra: all
Requires-Dist: dgread[dev,pandas]; extra == "all"
